fractionaldouble/__init__.py
fractionaldouble/critical_values.py
fractionaldouble/double_freq_test.py
fractionaldouble/fffff_test.py
fractionaldouble/utils.py
fractionaldouble/tests/__init__.py
fractionaldouble/tests/test_double_freq.py
fractionaldouble/tests/test_fffff.py
fractionaldouble-1.0.0.dist-info/METADATA
fractionaldouble-1.0.0.dist-info/WHEEL
fractionaldouble-1.0.0.dist-info/top_level.txt
fractionaldouble-1.0.0.dist-info/RECORD
