Metadata-Version: 2.4
Name: fractionaldouble
Version: 1.0.0
Summary: Fourier-based Unit Root Tests with Fractional and Double Frequencies
Author-email: Dr Merwan Roudane <merwanroudane920@gmail.com>
Maintainer-email: Dr Merwan Roudane <merwanroudane920@gmail.com>
License: MIT
Project-URL: Homepage, https://github.com/merwanroudane/fractionaldouble
Project-URL: Documentation, https://github.com/merwanroudane/fractionaldouble#readme
Project-URL: Repository, https://github.com/merwanroudane/fractionaldouble
Project-URL: Issues, https://github.com/merwanroudane/fractionaldouble/issues
Keywords: unit root test,Fourier,fractional frequency,double frequency,econometrics,time series,structural breaks,Dickey-Fuller,stationarity,FFFFF,cointegration
Classifier: Development Status :: 5 - Production/Stable
Classifier: Intended Audience :: Science/Research
Classifier: Intended Audience :: Education
Classifier: Intended Audience :: Financial and Insurance Industry
Classifier: License :: OSI Approved :: MIT License
Classifier: Operating System :: OS Independent
Classifier: Programming Language :: Python :: 3
Classifier: Programming Language :: Python :: 3.8
Classifier: Programming Language :: Python :: 3.9
Classifier: Programming Language :: Python :: 3.10
Classifier: Programming Language :: Python :: 3.11
Classifier: Programming Language :: Python :: 3.12
Classifier: Topic :: Scientific/Engineering
Classifier: Topic :: Scientific/Engineering :: Mathematics
Classifier: Topic :: Office/Business :: Financial :: Accounting
Requires-Python: >=3.8
Requires-Dist: numpy>=1.20.0
Requires-Dist: scipy>=1.7.0
Requires-Dist: pandas>=1.3.0
Provides-Extra: dev
Requires-Dist: pytest>=7.0.0; extra == "dev"
Requires-Dist: pytest-cov>=4.0.0; extra == "dev"
Requires-Dist: black>=22.0.0; extra == "dev"
Requires-Dist: isort>=5.10.0; extra == "dev"
Requires-Dist: flake8>=5.0.0; extra == "dev"
Requires-Dist: mypy>=0.990; extra == "dev"
Provides-Extra: docs
Requires-Dist: sphinx>=5.0.0; extra == "docs"
Requires-Dist: sphinx-rtd-theme>=1.0.0; extra == "docs"
Requires-Dist: numpydoc>=1.5.0; extra == "docs"
Provides-Extra: plotting
Requires-Dist: matplotlib>=3.5.0; extra == "plotting"
Provides-Extra: all
Requires-Dist: fractionaldouble[dev,docs,plotting]; extra == "all"
